{
  "name": "treydock-kdump",
  "version": "1.0.0",
  "author": "treydock",
  "summary": "Kdump Puppet module",
  "license": "Apache-2.0",
  "source": "https://github.com/treydock/puppet-kdump",
  "project_page": "https://github.com/treydock/puppet-kdump",
  "issues_url": "https://github.com/treydock/puppet-kdump/issues",
  "dependencies": [
    {
      "name": "puppetlabs/stdlib",
      "version_requirement": ">= 4.13.0 <10.0.0"
    },
    {
      "name": "puppet/augeasproviders_grub",
      "version_requirement": ">= 2.3.1 <6.0.0"
    }
  ],
  "operatingsystem_support": [
    {
      "operatingsystem": "RedHat",
      "operatingsystemrelease": [
        "7",
        "8"
      ]
    },
    {
      "operatingsystem": "CentOS",
      "operatingsystemrelease": [
        "7"
      ]
    },
    {
      "operatingsystem": "Rocky",
      "operatingsystemrelease": [
        "8"
      ]
    },
    {
      "operatingsystem": "Debian",
      "operatingsystemrelease": [
        "9"
      ]
    },
    {
      "operatingsystem": "Ubuntu",
      "operatingsystemrelease": [
        "18.04"
      ]
    }
  ],
  "requirements": [
    {
      "name": "puppet",
      "version_requirement": ">= 7.0.0 < 9.0.0"
    }
  ],
  "tags": [
    "kdump"
  ],
  "pdk-version": "2.7.1",
  "template-url": "https://github.com/treydock/pdk-templates#master",
  "template-ref": "heads/master-0-g76f4dbb"
}
